LICENSE
README.md
setup.py
apiscout/ApiQR.py
apiscout/ApiQRContext.py
apiscout/ApiScout.py
apiscout/ApiVector.py
apiscout/FingerprintCrawler.py
apiscout/IdaForm.py
apiscout/IdaProxy.py
apiscout/IdaTools.py
apiscout/ImportTableLoader.py
apiscout/OrdinalHelper.py
apiscout/PeTools.py
apiscout/__init__.py
apiscout/utility.py
apiscout.egg-info/PKG-INFO
apiscout.egg-info/SOURCES.txt
apiscout.egg-info/dependency_links.txt
apiscout.egg-info/requires.txt
apiscout.egg-info/top_level.txt
apiscout/data/html_frame.html
apiscout/data/winapi1024v1.txt
apiscout/data/winapi_contexts.csv