Metadata-Version: 2.1
Name: apiscout
Version: 1.2.0
Summary: A library for Windows API usage recovery and similarity assessment with focus on memory dumps.
Home-page: https://github.com/danielplohmann/apiscout
Author: Daniel Plohmann
Author-email: daniel.plohmann@mailbox.org
License: BSD 2-Clause
Platform: UNKNOWN
Classifier: Development Status :: 4 - Beta
Classifier: License :: OSI Approved :: BSD License
Classifier: Operating System :: OS Independent
Classifier: Programming Language :: Python :: 2.7
Classifier: Programming Language :: Python :: 3
Classifier: Topic :: Security
Classifier: Topic :: Software Development :: Disassemblers
